[
	{
		"name": "bluedog_E1_engine",
		"title": "E-1",
		"description": "",
		"mod": "Bluedog DB",
		"cost": 624,
		"entry_cost": 60000,
		"category": "ORBITAL",
		"info": "",
		"year": "1963",
		"technology": "orbitalRocketry1963",
		"era": "",
		"ro": true,
		"orphan": false,
		"rp0_conf": true,
		"spacecraft": "",
		"engine_config": "E1",
		"upgrade": false,
		"entry_cost_mods": "E-1",
		"identical_part_name": "E1",
		"module_tags": [
			"EngineLiquidTurbo"
		]
	},
	{
		"name": "bluedog_G1",
		"title": "G-1",
		"description": "",
		"mod": "Bluedog DB",
		"cost": 136,
		"entry_cost": 0,
		"category": "ORBITAL",
		"info": "",
		"year": "1961",
		"technology": "orbitalRocketry1961",
		"era": "",
		"ro": true,
		"orphan": false,
		"rp0_conf": true,
		"spacecraft": "",
		"engine_config": "G1",
		"upgrade": false,
		"entry_cost_mods": "G-1",
		"identical_part_name": "ROEE-G1",
		"module_tags": [
			"EngineLiquidPF"
		]
	},
	{
		"name": "bluedog_M1",
		"title": "M-1",
		"description": "",
		"mod": "Bluedog DB",
		"cost": 4914,
		"entry_cost": 0,
		"category": "HYDROLOX",
		"info": "",
		"year": "1970",
		"technology": "hydrolox1969",
		"era": "",
		"ro": true,
		"orphan": false,
		"rp0_conf": true,
		"spacecraft": "",
		"engine_config": "M1",
		"upgrade": false,
		"entry_cost_mods": "M-1-Spec",
		"identical_part_name": "M-1",
		"module_tags": [
			"EngineLiquidTurbo",
			"Hydrolox"
		]
	},
	{
		"name": "bluedog_MB60",
		"title": "MB-60",
		"description": "",
		"mod": "Bluedog DB",
		"cost": 1752,
		"entry_cost": 0,
		"category": "HYDROLOX",
		"info": "",
		"year": "2009",
		"technology": "hydrolox2009",
		"era": "",
		"ro": true,
		"orphan": false,
		"rp0_conf": true,
		"spacecraft": "",
		"engine_config": "MB60",
		"upgrade": false,
		"entry_cost_mods": "MB-60",
		"identical_part_name": "MB60",
		"module_tags": [
			"EngineLiquidTurbo",
			"Hydrolox"
		]
	},
	{
		"name": "bluedog_RL20_SL",
		"title": "RL-20 Sea Level",
		"description": "",
		"mod": "Bluedog DB",
		"cost": 2800,
		"entry_cost": 0,
		"category": "STAGED",
		"info": "",
		"year": "1976",
		"technology": "stagedCombustion1976",
		"era": "",
		"ro": true,
		"orphan": false,
		"rp0_conf": true,
		"spacecraft": "",
		"engine_config": "RL20",
		"upgrade": false,
		"entry_cost_mods": "StagedHydrolox",
		"identical_part_name": "RL20",
		"module_tags": [
			"EngineLiquidTurbo",
			"Hydrolox"
		]
	},
	{
		"name": "bluedog_RL20",
		"title": "RL-20 Multimode",
		"description": "",
		"mod": "Bluedog DB",
		"cost": 2800,
		"entry_cost": 0,
		"category": "STAGED",
		"info": "",
		"year": "1976",
		"technology": "stagedCombustion1976",
		"era": "",
		"ro": true,
		"orphan": false,
		"rp0_conf": true,
		"spacecraft": "",
		"engine_config": "RL20",
		"upgrade": false,
		"entry_cost_mods": "StagedHydrolox",
		"identical_part_name": "RL20",
		"module_tags": [
			"EngineLiquidTurbo",
			"Hydrolox"
		]
	},
	{
		"name": "bluedog_RS30",
		"title": "RS-30",
		"description": "",
		"mod": "Bluedog DB",
		"cost": 994,
		"entry_cost": 0,
		"category": "FRSC",
		"info": "",
		"year": "1979",
		"technology": "FRSC1976",
		"era": "",
		"ro": true,
		"orphan": false,
		"rp0_conf": true,
		"spacecraft": "",
		"engine_config": "RS30",
		"upgrade": false,
		"entry_cost_mods": "RS-30",
		"identical_part_name": "RS30",
		"module_tags": [
			"EngineLiquidTurbo",
			"Hydrolox"
		]
	},
	{
		"name": "bluedog_NERVA_XE",
		"title": "NERVA XE",
		"description": "",
		"mod": "Bluedog DB",
		"cost": 5788,
		"entry_cost": 0,
		"category": "NTR",
		"info": "",
		"year": "1972",
		"technology": "earlyNuclearPropulsion",
		"era": "",
		"ro": true,
		"orphan": false,
		"rp0_conf": true,
		"spacecraft": "",
		"engine_config": "NERVA_XE",
		"upgrade": false,
		"entry_cost_mods": "NERVA-XE-Hydrogen",
		"identical_part_name": "",
		"module_tags": [
			"EngineLiquidTurbo",
			"Nuclear"
		]
	},
	{
		"name": "bluedog_NERVA_FF",
		"title": "NERVA Full Flow Engine",
		"description": "",
		"mod": "Bluedog DB",
		"cost": 5976,
		"entry_cost": 0,
		"category": "NTR",
		"info": "",
		"year": "1972",
		"technology": "earlyNuclearPropulsion",
		"era": "",
		"ro": true,
		"orphan": false,
		"rp0_conf": true,
		"spacecraft": "",
		"engine_config": "NERVA_NRX",
		"upgrade": false,
		"entry_cost_mods": "NERVA-NRX-Hydrogen",
		"identical_part_name": "",
		"module_tags": [
			"EngineLiquidTurbo",
			"Nuclear"
		]
	},
	{
		"name": "bluedog_NERVA_FF_Aerospike",
		"title": "NERVA Full Flow Flight Aerospike Engine",
		"description": "",
		"mod": "Bluedog DB",
		"cost": 6164,
		"entry_cost": 0,
		"category": "NTR",
		"info": "",
		"year": "1981",
		"technology": "basicNuclearPropulsion",
		"era": "",
		"ro": true,
		"orphan": false,
		"rp0_conf": true,
		"spacecraft": "",
		"engine_config": "NERVA_NRX",
		"upgrade": false,
		"entry_cost_mods": "3000,bluedog-NERVA-FF",
		"identical_part_name": "",
		"module_tags": [
			"EngineLiquidTurbo",
			"Nuclear"
		]
	},
	{
		"name": "bluedog_NERVA_II",
		"title": "NERVA II",
		"description": "",
		"mod": "Bluedog DB",
		"cost": 11596,
		"entry_cost": 0,
		"category": "NTR",
		"info": "",
		"year": "1986",
		"technology": "improvedNuclearPropulsion",
		"era": "",
		"ro": true,
		"orphan": false,
		"rp0_conf": true,
		"spacecraft": "",
		"engine_config": "NERVAII",
		"upgrade": false,
		"entry_cost_mods": "NERVA-II",
		"identical_part_name": "",
		"module_tags": [
			"EngineLiquidTurbo",
			"Nuclear"
		]
	},
	{
		"name": "bluedog_smallNuclearEngine",
		"title": "Small Nuclear Engine",
		"description": "",
		"mod": "Bluedog DB",
		"cost": 3965,
		"entry_cost": 0,
		"category": "NTR",
		"info": "",
		"year": "1986",
		"technology": "improvedNuclearPropulsion",
		"era": "",
		"ro": true,
		"orphan": false,
		"rp0_conf": true,
		"spacecraft": "",
		"engine_config": "SmallEngine",
		"upgrade": false,
		"entry_cost_mods": "PEWEE100-Hydrogen",
		"identical_part_name": "",
		"module_tags": [
			"EngineLiquidTurbo",
			"Nuclear"
		]
	},
	{
		"name": "bluedog_XLR129",
		"title": "XLR-129",
		"description": "",
		"mod": "Bluedog DB",
		"cost": 3263,
		"entry_cost": 0,
		"category": "FRSC",
		"info": "",
		"year": "1974",
		"technology": "prototypeFRSC",
		"era": "",
		"ro": true,
		"orphan": false,
		"rp0_conf": true,
		"spacecraft": "",
		"engine_config": "LR129",
		"upgrade": false,
		"entry_cost_mods": "XLR129-P-1",
		"identical_part_name": "",
		"module_tags": [
			"EngineLiquidTurbo",
			"Hydrolox"
		]
	}
]